total_properties_pkg/__init__.py
total_properties_pkg/total_properties.py
example_pkg_totaljacketscpp-0.0.2.dist-info/LICENSE
example_pkg_totaljacketscpp-0.0.2.dist-info/METADATA
example_pkg_totaljacketscpp-0.0.2.dist-info/WHEEL
example_pkg_totaljacketscpp-0.0.2.dist-info/top_level.txt
example_pkg_totaljacketscpp-0.0.2.dist-info/RECORD
