Metadata-Version: 2.1
Name: example-pkg-totaljacketscpp
Version: 0.0.2
Summary: To calculate the total
Home-page: https://github.com/pypa/sampleproject
Author: AnkitaParande
Author-email: ankitaparande0210@gmail.com
License: UNKNOWN
Platform: UNKNOWN
Classifier: Programming Language :: Python :: 3
Classifier: License :: OSI Approved :: MIT License
Classifier: Operating System :: OS Independent
Requires-Python: >=3.6
License-File: LICENSE
